[
  {
    "name": "Sum",
    "canonical": "a + b",
    "answer": "a + b",
    "correct": true,
    "timestamp": 1663264773184
  },
  {
    "name": "Difference",
    "canonical": "a - b",
    "answer": "a - b",
    "correct": true,
    "timestamp": 1665024513509
  },
  {
    "name": "Product",
    "canonical": "a * b",
    "answer": "a * b",
    "correct": true,
    "timestamp": 1665024522127
  },
  {
    "name": "Ratio",
    "canonical": "a / b",
    "answer": "a / b",
    "correct": true,
    "timestamp": 1665024534288
  },
  {
    "name": "Remainder",
    "canonical": "a % b",
    "answer": "a % b",
    "correct": true,
    "timestamp": 1665024580668
  }
]